space_monkey/__init__.py
space_monkey/message_classifier_prompt.py
space_monkey/slack_app.py
space_monkey/utils.py
slide_space_monkey-6.3.0.dist-info/METADATA
slide_space_monkey-6.3.0.dist-info/WHEEL
slide_space_monkey-6.3.0.dist-info/RECORD
