Metadata-Version: 2.4
Name: slide-space-monkey
Version: 6.3.0
Summary: A simple, powerful way to deploy Tyler AI agents as Slack agents
Project-URL: Homepage, https://github.com/adamwdraper/slide
Project-URL: Repository, https://github.com/adamwdraper/slide
Project-URL: Bug Tracker, https://github.com/adamwdraper/slide/issues
Author: adamwdraper
License: MIT
Classifier: Development Status :: 3 - Alpha
Classifier: Intended Audience :: Developers
Classifier: License :: OSI Approved :: MIT License
Classifier: Operating System :: OS Independent
Classifier: Programming Language :: Python :: 3
Classifier: Programming Language :: Python :: 3.11
Classifier: Programming Language :: Python :: 3.12
Classifier: Programming Language :: Python :: 3.13
Classifier: Topic :: Communications :: Chat
Classifier: Topic :: Software Development :: Libraries :: Python Modules
Requires-Python: >=3.11
Requires-Dist: fastapi>=0.104.0
Requires-Dist: litellm>=1.75.3
Requires-Dist: openai>=1.99.2
Requires-Dist: pydantic>=2.10.0
Requires-Dist: python-dotenv>=1.0.0
Requires-Dist: requests>=2.32.0
Requires-Dist: slack-bolt>=1.23.0
Requires-Dist: slide-narrator>=6.3.0
Requires-Dist: slide-tyler>=6.3.0
Requires-Dist: uvicorn[standard]>=0.24.0
Requires-Dist: weave>=0.52.23
Provides-Extra: dev
Requires-Dist: coverage>=7.6.0; extra == 'dev'
Requires-Dist: pytest-asyncio>=0.25.0; extra == 'dev'
Requires-Dist: pytest-cov>=6.0.0; extra == 'dev'
Requires-Dist: pytest>=8.3.0; extra == 'dev'
